{
  "result_code": "200",
  "data": [
    {
      "text": "A",
      "children": [
        {
          "value": "3017,4311",
          "text": "阿尔法·罗密欧",
          "id": 480,
          "children": [
            {
              "value": "3017,4311",
              "text": "阿尔法·罗密欧",
              "id": 364
            }
          ]
        },
        {
          "value": "4525,4526,2363,350,349,348,346,333,320,318,314,310,307,302,301,293,292,3106,275,1831,270,268,1819,78,77,75,1534,73,71,66,63,1818,61,5571",
          "text": "奥迪",
          "id": 5,
          "children": [
            {
              "value": "4525,4526,2363,350,349,348,346,333,320,318,314,310,307,302,301,293,292,3106,275,1831,270,268,1819,78,77,75,1534,73,71,66,63,1818,61,5571",
              "text": "奥迪",
              "id": 6
            }
          ]
        },
        {
          "value": "5289",
          "text": "安凯客车",
          "id": 743,
          "children": [
            {
              "value": "5289",
              "text": "安凯",
              "id": 706
            }
          ]
        },
        {
          "value": "1019,2891,1142,1141,1099,3047,1232,1100,1189,2987,2766,3046,3045,4309",
          "text": "阿斯顿马丁",
          "id": 299,
          "children": [
            {
              "value": "1019,2891,1142,1141,1099,3047,1232,1100,1189,2987,2766,3046,3045,4309",
              "text": "阿斯顿马丁",
              "id": 163
            }
          ]
        },
        {
          "value": "3009",
          "text": "阿尔宾娜",
          "id": 479,
          "children": [
            {
              "value": "3009",
              "text": "阿尔宾娜",
              "id": 363
            }
          ]
        }
      ]
    },
    {
      "text": "B",
      "children": [
        {
          "value": "2749,3060,2747",
          "text": "比速汽车",
          "id": 419,
          "children": [
            {
              "value": "2749,3060,2747",
              "text": "比速",
              "id": 286
            }
          ]
        },
        {
          "value": "2970,2748",
          "text": "巴博斯",
          "id": 420,
          "children": [
            {
              "value": "2970,2748",
              "text": "巴博斯",
              "id": 287
            }
          ]
        },
        {
          "value": "872,339,1838,337,338,331,330,328,327,305,261,260,193,192,183,182,180,179,178,152,131,132,129,113,5572,112,114,111,110,1144,1101,1021,1145,1146,2220,1634,1516,1635,1517,1723,93,84,83,79,4467,4509,4508,2023,2024,2483",
          "text": "奔驰",
          "id": 6,
          "children": [
            {
              "value": "338",
              "text": "梅赛德斯-迈巴赫",
              "id": 66
            },
            {
              "value": "872,339,1838,337,331,330,328,327,305,261,260,193,192,183,182,180,179,178,152,131,132,129,113,5572,112,114,111,110,1144,1101,1021,1145,1146,2220,1634,1516,1635,1517,1723,93,84,83,79,4467,4509,4508,2023,2024,2483",
              "text": "奔驰",
              "id": 7
            }
          ]
        },
        {
          "value": "435,16,181,177,151,1820,130,1726",
          "text": "北京奔驰",
          "id": 7,
          "children": [
            {
              "value": "435,16",
              "text": "克莱斯勒",
              "id": 54
            },
            {
              "value": "181,177,151,1820,130,1726",
              "text": "奔驰",
              "id": 7
            }
          ]
        },
        {
          "value": "752,719,732",
          "text": "北京吉普",
          "id": 8,
          "children": [
            {
              "value": "752",
              "text": "JEEP",
              "id": 2
            },
            {
              "value": "719,732",
              "text": "三菱",
              "id": 83
            }
          ]
        },
        {
          "value": "4013,1143,1020,4012,1190,1233,2242,1555,1719,1714,2021,797,4771,796,4010,795,2163,794,4009,793,4008,4007,792,791,4011,869,4006,4005,155,154,4004,5512,90,974,1191,4425,3066,1859,1861,2162,4487,3067,2245,2505,4545,2205,2080,4770,2703",
          "text": "北京汽车",
          "id": 9,
          "children": [
            {
              "value": "4013,1143,1020,4012,1190,1233,2242,1555,1719,1714,2021,797,4771,796,4010,795,2163,794,4009,793,4008,4007,792,791,4011,869,4006,4005,155,154,4004,5512,90,974,1191,4425,3066,1859,1861,2162,4487,3067,2245,2505,4545,2205,2080,4770,2703",
              "text": "北京汽车",
              "id": 9
            }
          ]
        },
        {
          "value": "670,935,850,2281,5992,990,819,4014,642,5632,915,3014,940,702,1061,2776,700,930,4445,557,556,554,776,775,4548,2643,2889,787,4015,900,2099,5246",
          "text": "北京现代",
          "id": 10,
          "children": [
            {
              "value": "1061,2776",
              "text": "首望",
              "id": 133
            },
            {
              "value": "670,935,850,2281,5992,990,819,4014,642,5632,915,3014,940,702,700,930,4445,557,556,554,776,775,4548,2643,2889,787,4015,900,2099,5246",
              "text": "现代",
              "id": 90
            }
          ]
        },
        {
          "value": "406,1022",
          "text": "别克",
          "id": 11,
          "children": [
            {
              "value": "406,1022",
              "text": "别克",
              "id": 10
            }
          ]
        },
        {
          "value": "555,553,397,375,1841,372,371,1840,369,367,366,365,234,232,231,228,1856,55,4670,50,1814,42,45,44,34,1811,28,31,30,12,988,11,2,4,3,2019,5127",
          "text": "宝马",
          "id": 12,
          "children": [
            {
              "value": "555,553,397,375,1841,372,371,1840,369,367,366,365,234,232,231,228,1856,55,4670,50,1814,42,45,44,34,1811,28,31,30,12,988,11,2,4,3,2019,5127",
              "text": "宝马",
              "id": 11
            }
          ]
        },
        {
          "value": "1062,1518,1725,544,2566,543,542,2320,4376,2282,2887,4611",
          "text": "北汽幻速",
          "id": 13,
          "children": [
            {
              "value": "1062,1518,1725,544,2566,543,542,2320,4376,2282,2887,4611",
              "text": "北汽幻速",
              "id": 12
            }
          ]
        },
        {
          "value": "754,4018,634,833,4020,4017,958,4016,934,1192,1234,4019,1063,2705",
          "text": "北汽汽车",
          "id": 14,
          "children": [
            {
              "value": "754,4018,634,833,4020,4017,958,4016,934,1192,1234,4019,1063,2705",
              "text": "北汽汽车",
              "id": 13
            }
          ]
        },
        {
          "value": "1731,149,147,2199,2805,4746,2986,5832",
          "text": "北汽新能源",
          "id": 15,
          "children": [
            {
              "value": "1731,149,147,2199,2805,2986,5832",
              "text": "北京汽车",
              "id": 9
            },
            {
              "value": "4746",
              "text": "Arcfox",
              "id": 605
            }
          ]
        },
        {
          "value": "1848,622,1830,265,259,107,91,59,58,3085,3086,2753",
          "text": "保时捷",
          "id": 16,
          "children": [
            {
              "value": "1848,622,1830,265,259,107,91,59,58,3085,3086,2753",
              "text": "保时捷",
              "id": 14
            }
          ]
        },
        {
          "value": "835,1288,1147,1148,1329,1328,4022,1287,1064,4021,458,207,116",
          "text": "本田",
          "id": 17,
          "children": [
            {
              "value": "835,1288,1147,1148,1329,1328,4022,1287,1064,4021,458,207,116",
              "text": "本田",
              "id": 15
            }
          ]
        },
        {
          "value": "4039,826,4037,744,473,4038,827,4036,321,4035,319,4034,313,4033,235,4032,216,4031,170,2164,169,4030,4029,168,167,4028,161,4027,4026,4025,1822,160,159,4024,158,4023,143,1536,1716,1537,2523,1614,2346,5815,5712,968,1717,5039,5038,4450,3071,969,2625,5816,5511,2160,2119,4947,4565",
          "text": "比亚迪",
          "id": 18,
          "children": [
            {
              "value": "4039,826,4037,744,473,4038,827,4036,321,4035,319,4034,313,4033,235,4032,216,4031,170,2164,169,4030,4029,168,167,4028,161,4027,4026,4025,1822,160,159,4024,158,4023,143,1536,1716,1537,2523,1614,2346,5815,5712,968,1717,5039,5038,4450,3071,969,2625,5816,5511,2160,2119,4947,4565",
              "text": "比亚迪",
              "id": 16
            }
          ]
        },
        {
          "value": "5037,851",
          "text": "比亚迪戴姆勒",
          "id": 19,
          "children": [
            {
              "value": "5037,851",
              "text": "腾势",
              "id": 86
            }
          ]
        },
        {
          "value": "297,32,22,20,13,8,1065,1289,1235,1102,1236,5065",
          "text": "标致",
          "id": 20,
          "children": [
            {
              "value": "297,32,22,20,13,8,1065,1289,1235,1102,1236,5065",
              "text": "标致",
              "id": 17
            }
          ]
        },
        {
          "value": "4985",
          "text": "北汽瑞丽",
          "id": 663,
          "children": [
            {
              "value": "4985",
              "text": "北汽道达",
              "id": 626
            }
          ]
        },
        {
          "value": "1060",
          "text": "宝腾",
          "id": 282,
          "children": [
            {
              "value": "1060",
              "text": "宝腾",
              "id": 149
            }
          ]
        },
        {
          "value": "2989,5371,2183,5372",
          "text": "宝沃汽车",
          "id": 379,
          "children": [
            {
              "value": "2989,5371,2183,5372",
              "text": "宝沃",
              "id": 223
            }
          ]
        },
        {
          "value": "1023,2985,1237,1024,2767,2768",
          "text": "宾利",
          "id": 284,
          "children": [
            {
              "value": "1023,2985,1237,1024,2767,2768",
              "text": "宾利",
              "id": 150
            }
          ]
        },
        {
          "value": "483,481,4044,401,1290,4865,2807,2039,2340,4908,5351",
          "text": "北汽昌河",
          "id": 29,
          "children": [
            {
              "value": "483,481,4044,401,1290,4865,2807,2039,2340,4908,5351",
              "text": "昌河",
              "id": 21
            }
          ]
        }
      ]
    },
    {
      "text": "C",
      "children": [
        {
          "value": "4258,725,5427,4257,724,4407,4264,1103,1292,1330,1239,1194,1193,1067,4249,1195,1291,1293,1396,4527,4368,4613,2716,1397,1398,1105,4906,4388,2020,3070,5432,5428,4371,1740,5772",
          "text": "长安欧尚",
          "id": 339,
          "children": [
            {
              "value": "4258,725,5427,4257,724,4407,4264,1103,1292,1330,1239,1194,1193,1067,4249,1195,1291,1293,1396,4527,4368,4613,2716,1397,1398,1105,4906,4388,2020,3070,5432,5428,4371,1740,5772",
              "text": "长安",
              "id": 18
            }
          ]
        },
        {
          "value": "4245,139,138,4246,136,5131,1980,5125",
          "text": "长安标致雪铁龙",
          "id": 21,
          "children": [
            {
              "value": "4245,139,138,4246,136,5131,1980,5125",
              "text": "DS",
              "id": 1
            }
          ]
        },
        {
          "value": "1319",
          "text": "成功汽车",
          "id": 278,
          "children": [
            {
              "value": "1319",
              "text": "神剑",
              "id": 161
            }
          ]
        },
        {
          "value": "688,774,685,959,5206,2715,684,4248,920,4247,907,484,469,468,471,470,580,579,1399",
          "text": "长安福特",
          "id": 22,
          "children": [
            {
              "value": "688,774,685,959,5206,2715,684,4248,920,4247,907,484,469,468,471,470,580,579,1399",
              "text": "福特",
              "id": 33
            }
          ]
        },
        {
          "value": "948,497,672,416,855,854,853,757,1715,4374",
          "text": "长安铃木",
          "id": 23,
          "children": [
            {
              "value": "948,497,672,416,855,854,853,757,1715,4374",
              "text": "铃木",
              "id": 63
            }
          ]
        },
        {
          "value": "711,709,710,707,706,705,704,703,121",
          "text": "长安马自达",
          "id": 24,
          "children": [
            {
              "value": "711,709,710,707,706,705,704,703,121",
              "text": "马自达",
              "id": 68
            }
          ]
        },
        {
          "value": "5417,5416,5415,5414,4260,4907,4612,2722,1855,916,913,5423,4259,4618,764,1844,585,5424,4263,4262,4261,945,944,942,941,943,961,5425,4256,4255,424,423,422,4372,2720,421,4254,4253,128,127,4252,126,6073,4251,118,4250,117,1104,1240,1068,1066,1149,2166,5429,4507,1860,4488,2809,5426,2965,5132,3090,6035,5674",
          "text": "长安汽车",
          "id": 25,
          "children": [
            {
              "value": "5417,5416,5415,5414,4260,4907,4612,2722,1855,916,913,5423,4259,4618,764,1844,585,5424,4263,4262,4261,945,944,942,941,943,961,5425,4256,4255,424,423,422,4372,2720,421,4254,4253,128,127,4252,126,6073,4251,118,4250,117,1104,1240,1068,1066,1149,2166,5429,4507,1860,4488,2809,5426,2965,5132,3090",
              "text": "长安",
              "id": 18
            },
            {
              "value": "6035,5674",
              "text": "欧尚汽车",
              "id": 885
            }
          ]
        },
        {
          "value": "322,309",
          "text": "长安沃尔沃",
          "id": 26,
          "children": [
            {
              "value": "322,309",
              "text": "沃尔沃",
              "id": 87
            }
          ]
        },
        {
          "value": "4275,621,803,836,801,4274,575,4278,889,591,4280,523,992,522,4706,521,4705,520,4268,519,4269,518,4382,4279,2485,517,1535,4381,1738,516,4276,630,4267,360,4272,230,4271,226,4270,225,4266,104,5042,4277,2624,97,4265,95,1294,4273,6113,2339,3074,4766,4765,3087,4767,4405,2714,2713,4764,4518,6093,2726,4780,2708,2180,5248,5247,5188,5187,5653,5266",
          "text": "长城汽车",
          "id": 27,
          "children": [
            {
              "value": "3074,4766,4765,3087,4764,4518,6093,5653,5266",
              "text": "WEY",
              "id": 385
            },
            {
              "value": "4275,621,803,836,801,4274,575,4278,889,591,4276,630,4267,360,4272,230,4271,226,4270,225,4266,104,5042,4277,2624,97,4265,95,2339",
              "text": "长城",
              "id": 19
            },
            {
              "value": "4280,523,992,522,4706,521,4705,520,4268,519,4269,518,4382,4279,2485,517,1535,4381,1738,516,1294,4273,4767,4405,2714,2713,2726,4780,2708,2180,5248,5247,5188,5187",
              "text": "哈弗",
              "id": 38
            },
            {
              "value": "6113",
              "text": "欧拉",
              "id": 845
            }
          ]
        },
        {
          "value": "640,4043,743,4395,428,4040,4648,427,678,677,4042,4041,680,679,1238,2665",
          "text": "昌河铃木",
          "id": 28,
          "children": [
            {
              "value": "4043,743,4395,428,678,677",
              "text": "昌河铃木",
              "id": 22
            },
            {
              "value": "640,4040,4648,427,4042,4041,680,679,1238,2665",
              "text": "铃木",
              "id": 63
            }
          ]
        }
      ]
    },
    {
      "text": "D",
      "children": [
        {
          "value": "494,4685,681,4749,592,4673,4383,596,595,594,593,4052,1333,1070,1071,1519,2181,2364",
          "text": "东风柳汽",
          "id": 32,
          "children": [
            {
              "value": "494,4685,681,4749,592,4673,4383,596,595,594,593,4052,1333,1070,1071,1519,2181,2364",
              "text": "东风风行",
              "id": 26
            }
          ]
        },
        {
          "value": "137,135,134",
          "text": "DS",
          "id": 1,
          "children": [
            {
              "value": "137,135,134",
              "text": "DS",
              "id": 1
            }
          ]
        },
        {
          "value": "1058,1108,917,4927,4566,2709,5533",
          "text": "东风汽车",
          "id": 33,
          "children": [
            {
              "value": "1058,4927,2709,5533",
              "text": "东风",
              "id": 23
            },
            {
              "value": "1108,917,4566",
              "text": "东风御风",
              "id": 28
            }
          ]
        },
        {
          "value": "1106",
          "text": "大发",
          "id": 258,
          "children": [
            {
              "value": "1106",
              "text": "大发",
              "id": 123
            }
          ]
        },
        {
          "value": "746,590,4057,669,914,918,888,4058,5833,903,902,653,682,650,748,844,1654,3088,2139",
          "text": "东风日产",
          "id": 34,
          "children": [
            {
              "value": "746,590,4057,669,914,918,888,4058,5833,903,902,653,682,650,748,844,1654,3088,2139",
              "text": "日产",
              "id": 75
            }
          ]
        },
        {
          "value": "1025,1331,1241,1295",
          "text": "大迪汽车",
          "id": 291,
          "children": [
            {
              "value": "1025,1331,1241,1295",
              "text": "大迪",
              "id": 134
            }
          ]
        },
        {
          "value": "1153,1334,4506,1243,3059,4528,2244,463",
          "text": "东风小康",
          "id": 35,
          "children": [
            {
              "value": "1153,1334,4506,1243,3059,4528,2244,463",
              "text": "东风小康",
              "id": 27
            }
          ]
        },
        {
          "value": "777,922,814,811,881,482,823,957,567,751,6074,412,5821,2319,213,4517,212,4063,211,210,4516,208,209,1244,1072,2885,4567,2025,5952",
          "text": "东风悦达起亚",
          "id": 36,
          "children": [
            {
              "value": "1244",
              "text": "华骐",
              "id": 164
            },
            {
              "value": "777,922,814,811,881,482,823,957,567,751,6074,412,5821,2319,213,4517,212,4063,211,210,4516,208,209,1072,2885,4567,2025,5952",
              "text": "起亚",
              "id": 74
            }
          ]
        },
        {
          "value": "282,273",
          "text": "东风英菲尼迪",
          "id": 37,
          "children": [
            {
              "value": "282,273",
              "text": "英菲尼迪",
              "id": 94
            }
          ]
        },
        {
          "value": "718,447,446,906,237,2826,4571,2407",
          "text": "东风裕隆",
          "id": 38,
          "children": [
            {
              "value": "2826",
              "text": "裕路",
              "id": 465
            },
            {
              "value": "718,447,446,906,237,4571,2407",
              "text": "纳智捷",
              "id": 69
            }
          ]
        },
        {
          "value": "2707,2059",
          "text": "东风雷诺",
          "id": 359,
          "children": [
            {
              "value": "2707,2059",
              "text": "雷诺",
              "id": 64
            }
          ]
        },
        {
          "value": "452,4067,1154,1739,1383,2725,4910,2683,460,656,659,658,652,933,505,453,475,474,566,602,4066,358,4606,4065,357,4064,354",
          "text": "东南汽车",
          "id": 39,
          "children": [
            {
              "value": "460,656,659,933,505,566",
              "text": "三菱",
              "id": 83
            },
            {
              "value": "452",
              "text": "克莱斯勒",
              "id": 54
            },
            {
              "value": "4067,1154,1739,1383,2725,4910,2683,658,652,453,475,474,4066,358,4606,4065,357,4064,354",
              "text": "东南",
              "id": 29
            },
            {
              "value": "602",
              "text": "道奇",
              "id": 30
            }
          ]
        },
        {
          "value": "1242",
          "text": "大马汽车",
          "id": 296,
          "children": [
            {
              "value": "1242",
              "text": "大马",
              "id": 158
            }
          ]
        },
        {
          "value": "1297,1069,1332,5185,502,1843,504,1853,848,701,699,290,289,545,574,808,890,607,1839,352,343,256,145,109,1152,1027,4345,1919,2549,2550",
          "text": "大众",
          "id": 40,
          "children": [
            {
              "value": "1297,1069,1332,5185,502,1843,504,1853,848,701,699,290,289,545,574,808,890,607,1839,352,343,256,145,109,1152,1027,4345,1919,2549,2550",
              "text": "大众",
              "id": 31
            }
          ]
        },
        {
          "value": "4667",
          "text": "电咖汽车",
          "id": 561,
          "children": [
            {
              "value": "4667",
              "text": "电咖",
              "id": 505
            }
          ]
        },
        {
          "value": "441,3053,291,133,342,288,2751,4609",
          "text": "东风启辰",
          "id": 439,
          "children": [
            {
              "value": "441,3053,291,133,342,288,2751,4609",
              "text": "启辰",
              "id": 72
            }
          ]
        },
        {
          "value": "1150,1196,1151,1296,1026",
          "text": "大宇",
          "id": 280,
          "children": [
            {
              "value": "1150,1196,1151,1296,1026",
              "text": "大宇",
              "id": 151
            }
          ]
        },
        {
          "value": "4045,409,561,817,2785,798,837,389,4367,115,1574,2644,3005,5451",
          "text": "东风本田",
          "id": 30,
          "children": [
            {
              "value": "817",
              "text": "思铭",
              "id": 84
            },
            {
              "value": "4045,409,561,2785,798,837,389,4367,115,1574,2644,3005,5451",
              "text": "本田",
              "id": 15
            }
          ]
        },
        {
          "value": "2289,1732,488,4055,308,221,4054,199,2239,82,4053,76,2022,67,4605,1979,4530,2724,4647,4523",
          "text": "东风乘用车",
          "id": 31,
          "children": [
            {
              "value": "2289,1732,488,4055,308,221,4054,199,2239,82,4053,76,2022,67,4605,1979,4530,2724,4647,4523",
              "text": "东风风神",
              "id": 25
            }
          ]
        }
      ]
    },
    {
      "text": "F",
      "children": [
        {
          "value": "1199",
          "text": "菲斯克",
          "id": 292,
          "children": [
            {
              "value": "1199",
              "text": "菲斯克",
              "id": 153
            }
          ]
        },
        {
          "value": "2285,1075,2745,2286,1959",
          "text": "福汽启腾",
          "id": 279,
          "children": [
            {
              "value": "2285,1075,2745,2286,1959",
              "text": "启腾",
              "id": 126
            }
          ]
        },
        {
          "value": "1031,1341,1201,1299,982",
          "text": "福迪汽车",
          "id": 119,
          "children": [
            {
              "value": "1031,1341,1201,1299,982",
              "text": "福迪",
              "id": 103
            }
          ]
        },
        {
          "value": "868,871,668,2060",
          "text": "福建奔驰",
          "id": 41,
          "children": [
            {
              "value": "868,871,668,2060",
              "text": "奔驰",
              "id": 7
            }
          ]
        },
        {
          "value": "1198,1028,1246,1245,1029,1335,1197,1109,1030,4307,4520,2988,3057,3056,3058,4671,4308,5287",
          "text": "法拉利",
          "id": 297,
          "children": [
            {
              "value": "1198,1028,1246,1245,1029,1335,1197,1109,1030,4307,4520,2988,3057,3056,3058,4671,4308,5287",
              "text": "法拉利",
              "id": 165
            }
          ]
        },
        {
          "value": "540,740,737,643,294,56,576,867,404,163,1156,1111,1073,1339,1249,1298,1340,1157,1248,1155,1110,1337,1200,1338,1336,2770,2777",
          "text": "丰田",
          "id": 42,
          "children": [
            {
              "value": "540,740,737,643,294,56,576,867,404,163,1156,1111,1073,1339,1249,1298,1340,1157,1248,1155,1110,1337,1200,1338,1336,2770,2777",
              "text": "丰田",
              "id": 32
            }
          ]
        },
        {
          "value": "1074",
          "text": "福祐汽车",
          "id": 267,
          "children": [
            {
              "value": "1074",
              "text": "福祐",
              "id": 135
            }
          ]
        },
        {
          "value": "773,931,467,852,578,1077,1112,1202,1250,1252,1251,1158,1078,1032,1079,1076,4346,4622,3025,2778,2779,5551",
          "text": "福特",
          "id": 43,
          "children": [
            {
              "value": "773,931,467,852,578,1077,1112,1202,1250,1252,1251,1158,1078,1032,1079,1076,4346,4622,3025,2778,2779,5551",
              "text": "福特",
              "id": 33
            }
          ]
        },
        {
          "value": "1253,4068,1113,1300,4070,2783,2782,1342,5255,4946,4945,2290,1301,5332,2895,2894,2781,2780,4069,690,2284,971,2787",
          "text": "福田汽车",
          "id": 44,
          "children": [
            {
              "value": "1253,4068,1113,1300,4070,2783,2782,1342,5255,4946,4945,2290,1301,5332,2895,2894,2781,2780,4069,690,2284,971,2787",
              "text": "福田",
              "id": 34
            }
          ]
        },
        {
          "value": "673,496,727,438,35,1247",
          "text": "菲亚特",
          "id": 45,
          "children": [
            {
              "value": "673,496,727,438,35,1247",
              "text": "菲亚特",
              "id": 35
            }
          ]
        },
        {
          "value": "1204,1203",
          "text": "富奇汽车",
          "id": 303,
          "children": [
            {
              "value": "1204,1203",
              "text": "富奇",
              "id": 159
            }
          ]
        }
      ]
    },
    {
      "text": "G",
      "children": [
        {
          "value": "1849,651,929,950,2967,962,530,613,1847,612,6115,5257",
          "text": "广汽丰田",
          "id": 48,
          "children": [
            {
              "value": "1849,651,929,950,2967,962,530,613,1847,612,6115,5257",
              "text": "丰田",
              "id": 32
            }
          ]
        },
        {
          "value": "4074,490,963,1694,2259,2761,5265,5872",
          "text": "广汽菲亚特克莱斯勒",
          "id": 49,
          "children": [
            {
              "value": "1694,2259,2761,5265,5872",
              "text": "JEEP",
              "id": 2
            },
            {
              "value": "4074,490,963",
              "text": "菲亚特",
              "id": 35
            }
          ]
        },
        {
          "value": "4075,1114,1302,4079,1254,1343,4078,1205,1206,4077,1733,891,4076,420,419,153",
          "text": "广汽吉奥",
          "id": 50,
          "children": [
            {
              "value": "4075,1114,1302,4079,1254,1343,4078,1205,1206,4077,1733,891,4076,420,419,153",
              "text": "吉奥",
              "id": 46
            }
          ]
        },
        {
          "value": "731,728,4080,586,2563,4569,5892",
          "text": "广汽三菱",
          "id": 51,
          "children": [
            {
              "value": "731,728,4080,586,2563,5892",
              "text": "三菱",
              "id": 83
            },
            {
              "value": "4569",
              "text": "广汽传祺",
              "id": 36
            }
          ]
        },
        {
          "value": "512,513,511,2003",
          "text": "观致汽车",
          "id": 52,
          "children": [
            {
              "value": "512,513,511,2003",
              "text": "观致",
              "id": 37
            }
          ]
        },
        {
          "value": "1034,1033",
          "text": "光冈",
          "id": 277,
          "children": [
            {
              "value": "1034,1033",
              "text": "光冈",
              "id": 142
            }
          ]
        },
        {
          "value": "4619",
          "text": "国金汽车",
          "id": 541,
          "children": [
            {
              "value": "4619",
              "text": "国金",
              "id": 446
            }
          ]
        },
        {
          "value": "4620,5308,2384,2627,461,459,2603,919,462,1514,440,510,799,403,654,306,2202",
          "text": "广汽本田",
          "id": 46,
          "children": [
            {
              "value": "306",
              "text": "理念",
              "id": 65
            },
            {
              "value": "4620,5308,2384",
              "text": "讴歌",
              "id": 71
            },
            {
              "value": "2627,461,459,2603,919,462,1514,440,510,799,403,654,2202",
              "text": "本田",
              "id": 15
            }
          ]
        },
        {
          "value": "4073,186,187,5126,4325,185,174,5045,4072,173,1824,3075,4071,171,172,4406,4511,2167,4373,4845,4965,2405",
          "text": "广汽乘用车",
          "id": 47,
          "children": [
            {
              "value": "4073,186,187,5126,4325,185,174,5045,4072,173,1824,3075,4071,171,172,4406,4511,2167,4373,4845,4965,2405",
              "text": "广汽传祺",
              "id": 36
            }
          ]
        },
        {
          "value": "1575,1576,1577,1578",
          "text": "广州宝龙",
          "id": 319,
          "children": [
            {
              "value": "1575,1576,1577,1578",
              "text": "宝龙",
              "id": 202
            }
          ]
        },
        {
          "value": "1230,1286,1098,1188,2752",
          "text": "GMC",
          "id": 287,
          "children": [
            {
              "value": "1230,1286,1098,1188,2752",
              "text": "GMC",
              "id": 152
            }
          ]
        }
      ]
    },
    {
      "text": "H",
      "children": [
        {
          "value": "1037",
          "text": "海格汽车",
          "id": 257,
          "children": [
            {
              "value": "1037",
              "text": "海格汽车",
              "id": 124
            }
          ]
        },
        {
          "value": "1115,1347",
          "text": "航天汽车",
          "id": 265,
          "children": [
            {
              "value": "1115,1347",
              "text": "航天汽车",
              "id": 137
            }
          ]
        },
        {
          "value": "1116",
          "text": "黑豹汽车",
          "id": 300,
          "children": [
            {
              "value": "1116",
              "text": "黑豹",
              "id": 127
            }
          ]
        },
        {
          "value": "5752",
          "text": "红星汽车",
          "id": 783,
          "children": [
            {
              "value": "5752",
              "text": "红星汽车",
              "id": 745
            }
          ]
        },
        {
          "value": "4674,2565,4911,4610",
          "text": "汉腾汽车",
          "id": 399,
          "children": [
            {
              "value": "4674,2565,4911,4610",
              "text": "汉腾",
              "id": 263
            }
          ]
        },
        {
          "value": "4097,2954,364,1815,43,29,1258,2664,2886,2061,5311",
          "text": "华晨宝马",
          "id": 53,
          "children": [
            {
              "value": "1258,2664",
              "text": "之诺",
              "id": 128
            },
            {
              "value": "4097,2954,364,1815,43,29,2886,2061,5311",
              "text": "宝马",
              "id": 11
            }
          ]
        },
        {
          "value": "4099,455,508,763,558,960,4098,312,1348,1129,1303,1730,4773,541,2786,4772,3054",
          "text": "华晨金杯",
          "id": 54,
          "children": [
            {
              "value": "4099,455,508,763,558,960,4098,312,1348,1129,1303,1730,2786,4772,3054",
              "text": "金杯",
              "id": 48
            },
            {
              "value": "4773,541",
              "text": "华颂",
              "id": 44
            }
          ]
        },
        {
          "value": "53,1724,4913,2465,6033,4326",
          "text": "华晨鑫源",
          "id": 55,
          "children": [
            {
              "value": "53,1724",
              "text": "金杯",
              "id": 48
            },
            {
              "value": "2465,6033,4326",
              "text": "斯威",
              "id": 243
            },
            {
              "value": "4913",
              "text": "鑫源",
              "id": 585
            }
          ]
        },
        {
          "value": "4109,4108,4107,4106,4105,573,572,571,570,569,597,4111,951,954,4110,953,4104,356,1015,353,4103,202,4102,201,200,2898,4778,4101,198,4100,197,1038,1259,4390,2888,5034,4549,5819,5190",
          "text": "华晨中华",
          "id": 56,
          "children": [
            {
              "value": "4109,4108,4107,4106,4105,573,572,571,570,569,597,4111,951,954,4110,953,4104,356,1015,353,4103,202,4102,201,200,2898,4778,4101,198,4100,197,1038,1259,4390,2888,5034,4549,5819,5190",
              "text": "中华",
              "id": 98
            }
          ]
        },
        {
          "value": "4081,631,4082,816,4302,790,1345,1256,1255,1081,4707,1036,1160,1080,1344,1159",
          "text": "哈飞汽车",
          "id": 57,
          "children": [
            {
              "value": "4081,631,4082,816,4302,790,1345,1256,1255,1081,4707,1036,1160,1080,1344,1159",
              "text": "哈飞",
              "id": 39
            }
          ]
        },
        {
          "value": "1208,4118,1039,1040,1349,1260,1579,4117,755",
          "text": "黄海汽车",
          "id": 58,
          "children": [
            {
              "value": "1208,4118,1039,1040,1349,1260,1579,4117,755",
              "text": "黄海",
              "id": 40
            }
          ]
        },
        {
          "value": "4092,753,4088,4087,4086,4085,479,478,476,480,4761,4090,532,4303,4089,531,5411,524,514,4091,738,1760,4093,745,5412,317,4774,4084,3015,311,4083,236,233,2288,2002,5491",
          "text": "海马汽车",
          "id": 59,
          "children": [
            {
              "value": "4092,753,4088,4087,4086,4085,479,478,476,480,4761,4090,532,4303,4089,531,5411,524,514,4091,738,1760,4093,745,5412,317,4774,4084,3015,311,4083,236,233,2288,2002,5491",
              "text": "海马",
              "id": 41
            }
          ]
        },
        {
          "value": "4096,533,4094,2728,227,1346,4095",
          "text": "海马郑州",
          "id": 60,
          "children": [
            {
              "value": "4096,533,4094,2728,227,1346,4095",
              "text": "海马",
              "id": 41
            }
          ]
        },
        {
          "value": "4114,661,4116,846,4113,432,1494,4115,800,4112,86,1117,4512,5421,5420,4408,4304,3065,2403,2321,4386,2026,4676,5422,5310",
          "text": "华泰汽车",
          "id": 61,
          "children": [
            {
              "value": "4114,661,4116,846,4113,432,1494,4115,800,4112,86,1117,4512,5421,5420,4408,4304,3065,2403,2321,4386,2026,4676,5422,5310",
              "text": "华泰",
              "id": 45
            }
          ]
        },
        {
          "value": "1257,1207,1161",
          "text": "悍马",
          "id": 286,
          "children": [
            {
              "value": "1257,1207,1161",
              "text": "悍马",
              "id": 154
            }
          ]
        }
      ]
    },
    {
      "text": "J",
      "children": [
        {
          "value": "1350",
          "text": "金程汽车",
          "id": 272,
          "children": [
            {
              "value": "1350",
              "text": "金程汽车",
              "id": 144
            }
          ]
        },
        {
          "value": "3068,4153,2583,932,437,563,901,2546,4147,487,4146,464,4152,378,4151,376,4149,373,4148,368,1162,1394,4150,1434,1675,2159,3094,2564,4915,4885,1939,4370,5253",
          "text": "江铃汽车",
          "id": 64,
          "children": [
            {
              "value": "563,901,2546,1675,2159",
              "text": "福特",
              "id": 33
            },
            {
              "value": "3068,4153,2583,932,437,1162,1394,3094,2564,4915,1939,5253",
              "text": "江铃",
              "id": 50
            },
            {
              "value": "4147,487,4146,464,4152,378,4151,376,4149,373,4148,368,4150,1434,4885,4370",
              "text": "陆风",
              "id": 58
            }
          ]
        },
        {
          "value": "4134,588,5823,4133,4131,885,886,565,4129,921,536,534,927,926,4130,966,696,691,4124,693,4128,896,4122,883,5044,4762,4378,4119,879,4448,1854,880,4121,5532,5531,434,4132,351,336,325,324,323,2424,4127,191,2406,190,4126,175,4120,144,4125,1041,2927,5471,2182,5036,4513,4466,4387,2990,2287,2100,2928,2544,5912,5041,4614,5035,4675,5268,5822",
          "text": "吉利汽车",
          "id": 65,
          "children": [
            {
              "value": "4134,588,5823,4133,4131,885,886,565,4129,921,536,534,927,926,4130,966,696,691,4124,693,4128,896,4122,883,5044,4762,4378,4119,879,4448,1854,880,4121,5532,5531,434,4132,351,336,325,324,323,2424,4127,191,2406,190,4126,175,4120,144,4125,1041,2927,5471,2182,5036,4513,4466,4387,2990,2287,2100,2928,2544,5035,4675,5822",
              "text": "吉利",
              "id": 51
            },
            {
              "value": "5912,5041,4614,5268",
              "text": "领克",
              "id": 445
            }
          ]
        },
        {
          "value": "6054,5031,4666,5165",
          "text": "君马汽车",
          "id": 642,
          "children": [
            {
              "value": "6054,5031,4666,5165",
              "text": "君马",
              "id": 485
            }
          ]
        },
        {
          "value": "967,965,689,956,454,1018,1231,2547",
          "text": "JEEP",
          "id": 2,
          "children": [
            {
              "value": "967,965,689,956,454,1018,1231,2547",
              "text": "JEEP",
              "id": 2
            }
          ]
        },
        {
          "value": "984",
          "text": "江西五十铃",
          "id": 121,
          "children": [
            {
              "value": "984",
              "text": "五十铃",
              "id": 105
            }
          ]
        },
        {
          "value": "2945,5307",
          "text": "九龙汽车",
          "id": 459,
          "children": [
            {
              "value": "2945,5307",
              "text": "九龙",
              "id": 343
            }
          ]
        },
        {
          "value": "1082,1304,1580,834,1850,4586,660,495,493,492,2946,866,387,386,385,384,383,157,156,4446,5105,663,1851,666",
          "text": "捷豹路虎",
          "id": 62,
          "children": [
            {
              "value": "834,1850,4586,660,495,493,492,2946,866,4446,663,1851,666",
              "text": "路虎",
              "id": 59
            },
            {
              "value": "1082,1304,1580,387,386,385,384,383,157,156,5105",
              "text": "捷豹",
              "id": 47
            }
          ]
        },
        {
          "value": "1209",
          "text": "吉林通田",
          "id": 271,
          "children": [
            {
              "value": "1209",
              "text": "通田",
              "id": 143
            }
          ]
        },
        {
          "value": "4143,786,2925,1718,4486,4394,4142,4141,4140,4137,765,551,4909,3013,2545,2929,2827,1761,1515,769,768,767,766,2706,2200,5675,4912,4465,2830,568,897,4145,947,4135,439,4139,550,4144,549,548,4138,4136,552,1042,1261,977,2243,5309",
          "text": "江淮汽车",
          "id": 63,
          "children": [
            {
              "value": "4143,786,2925,1718,4486,4394,4142,4141,4140,4137,765,551,4909,3013,2545,2929,2827,1761,1515,769,768,767,766,2706,2200,5675,4912,4465,2830,568,897,4145,947,4135,439,4139,550,4144,549,548,4138,4136,552,1042,1261,977,2243,5309",
              "text": "江淮",
              "id": 49
            }
          ]
        }
      ]
    },
    {
      "text": "K",
      "children": [
        {
          "value": "601,600,4929,2342,2344,1941,5820,6194",
          "text": "康迪",
          "id": 66,
          "children": [
            {
              "value": "601,600,4929,2342,2344,1941,5820,6194",
              "text": "康迪",
              "id": 52
            }
          ]
        },
        {
          "value": "1845,605,388,334,120,80,1119,1351,1210,1262",
          "text": "凯迪拉克",
          "id": 67,
          "children": [
            {
              "value": "1845,605,388,334,120,80,1119,1351,1210,1262",
              "text": "凯迪拉克",
              "id": 53
            }
          ]
        },
        {
          "value": "619,598,4930,451,15,1043,1263,1120,1352,1354,1165,1164,1305,1306,1353,1083,1211,2769,3061,5433",
          "text": "克莱斯勒",
          "id": 68,
          "children": [
            {
              "value": "4930,451,15,1043,1263,1120,1352,1354,1165,1164,1305,1306,1353,1083,1211,5433",
              "text": "克莱斯勒",
              "id": 54
            },
            {
              "value": "619,598,2769,3061",
              "text": "道奇",
              "id": 30
            }
          ]
        },
        {
          "value": "624,623,4524,2404,2283,4177,140",
          "text": "凯翼汽车",
          "id": 69,
          "children": [
            {
              "value": "624,623,4524,2404,2283,4177,140",
              "text": "凯翼",
              "id": 56
            }
          ]
        },
        {
          "value": "1118,4572,2773,4366,4751,5391",
          "text": "卡威汽车",
          "id": 281,
          "children": [
            {
              "value": "1118,4572,2773,4366,4751,5391",
              "text": "卡威",
              "id": 145
            }
          ]
        }
      ]
    },
    {
      "text": "L",
      "children": [
        {
          "value": "2890,1044,1166,1121,3051,2772,5286",
          "text": "兰博基尼",
          "id": 256,
          "children": [
            {
              "value": "2890,1044,1166,1121,3051,2772,5286",
              "text": "兰博基尼",
              "id": 125
            }
          ]
        },
        {
          "value": "1084,1307,1212,1308,1355,3006",
          "text": "劳斯莱斯",
          "id": 260,
          "children": [
            {
              "value": "1084,1307,1212,1308,1355,3006",
              "text": "劳斯莱斯",
              "id": 129
            }
          ]
        },
        {
          "value": "1167,1357,1122,635,636,970,4783,3076,529,750,2949,489,632,5285,5972",
          "text": "猎豹汽车",
          "id": 70,
          "children": [
            {
              "value": "1167,1357,1122,635,636,970,4783,3076,529,750,2949,489,632,5285,5972",
              "text": "长丰",
              "id": 20
            }
          ]
        },
        {
          "value": "1265,1045,1311",
          "text": "路特斯",
          "id": 263,
          "children": [
            {
              "value": "1265,1045,1311",
              "text": "路特斯",
              "id": 138
            }
          ]
        },
        {
          "value": "1356,4168,1309,4166,4165,486,4164,374,4163,370,4161,51,4160,48,4159,47,1816,4158,40,4157,4156,39,38,4155,25,1810,4154,24,5419,5025,4162,972,4167,975,4768,2896,4782,4760,3027,4769,2219,4916,1940,5592,5033,5026",
          "text": "力帆",
          "id": 71,
          "children": [
            {
              "value": "1356,4168,1309,4166,4165,486,4164,374,4163,370,4161,51,4160,48,4159,47,1816,4158,40,4157,4156,39,38,4155,25,1810,4154,24,5419,5025,4162,972,4167,975,4768,2896,4782,4760,3027,4769,2219,4916,1940,5592,5033,5026",
              "text": "力帆",
              "id": 57
            }
          ]
        },
        {
          "value": "1358,1310,1359,1168,1215,3072,255,254,2723,2771",
          "text": "林肯",
          "id": 72,
          "children": [
            {
              "value": "1358,1310,1359,1168,1215,3072,255,254,2723,2771",
              "text": "林肯",
              "id": 61
            }
          ]
        },
        {
          "value": "1213,1836,303,296,1829,264,224,1827,223,206,189,1825,184,1821,146,119,4925",
          "text": "雷克萨斯",
          "id": 73,
          "children": [
            {
              "value": "1213,1836,303,296,1829,264,224,1827,223,206,189,1825,184,1821,146,119,4925",
              "text": "雷克萨斯",
              "id": 62
            }
          ]
        },
        {
          "value": "840,442,577,629,4515",
          "text": "铃木",
          "id": 74,
          "children": [
            {
              "value": "840,442,577,629,4515",
              "text": "铃木",
              "id": 63
            }
          ]
        },
        {
          "value": "5894",
          "text": "领途汽车",
          "id": 843,
          "children": [
            {
              "value": "5894",
              "text": "领途汽车",
              "id": 805
            }
          ]
        },
        {
          "value": "1264,472,465,448,857,603,687,686,648,847,997,2828",
          "text": "雷诺",
          "id": 75,
          "children": [
            {
              "value": "1264,472,465,448,857,603,687,686,648,847,997,2828",
              "text": "雷诺",
              "id": 64
            }
          ]
        },
        {
          "value": "1266,1216",
          "text": "罗孚",
          "id": 301,
          "children": [
            {
              "value": "1266,1216",
              "text": "罗孚",
              "id": 167
            }
          ]
        },
        {
          "value": "1085",
          "text": "龙豹汽车",
          "id": 270,
          "children": [
            {
              "value": "1085",
              "text": "龙豹",
              "id": 166
            }
          ]
        },
        {
          "value": "3093",
          "text": "拉达汽车",
          "id": 501,
          "children": [
            {
              "value": "3093",
              "text": "拉达",
              "id": 405
            }
          ]
        }
      ]
    },
    {
      "text": "M",
      "children": [
        {
          "value": "1169",
          "text": "迈巴赫",
          "id": 290,
          "children": [
            {
              "value": "1169",
              "text": "迈巴赫",
              "id": 160
            }
          ]
        },
        {
          "value": "253,252,251,250,249,248,247",
          "text": "MINI",
          "id": 3,
          "children": [
            {
              "value": "253,252,251,250,249,248,247",
              "text": "MINI",
              "id": 4
            }
          ]
        },
        {
          "value": "1267,1268,1217,194,2079",
          "text": "玛莎拉蒂",
          "id": 76,
          "children": [
            {
              "value": "1267,1268,1217,194,2079",
              "text": "玛莎拉蒂",
              "id": 67
            }
          ]
        },
        {
          "value": "1046,2991,3048,4310,2754,5254,3049,2755,3050,2756,2757,3077,5732",
          "text": "迈凯伦",
          "id": 269,
          "children": [
            {
              "value": "1046,2991,3048,4310,2754,5254,3049,2755,3050,2756,2757,3077,5732",
              "text": "迈凯伦",
              "id": 139
            }
          ]
        },
        {
          "value": "708,122,4669,85,712,304,257,125,124",
          "text": "马自达",
          "id": 77,
          "children": [
            {
              "value": "708,122,4669,85,712,304,257,125,124",
              "text": "马自达",
              "id": 68
            }
          ]
        }
      ]
    },
    {
      "text": "N",
      "children": [
        {
          "value": "1386",
          "text": "南昌汽车",
          "id": 304,
          "children": [
            {
              "value": "1386",
              "text": "南昌汽车",
              "id": 174
            }
          ]
        },
        {
          "value": "1312",
          "text": "南京汽车",
          "id": 298,
          "children": [
            {
              "value": "1312",
              "text": "南京汽车",
              "id": 168
            }
          ]
        },
        {
          "value": "904,733,734,955",
          "text": "南京菲亚特",
          "id": 78,
          "children": [
            {
              "value": "904,733,734,955",
              "text": "菲亚特",
              "id": 35
            }
          ]
        },
        {
          "value": "456,426,4826",
          "text": "南京依维柯",
          "id": 79,
          "children": [
            {
              "value": "456,426,4826",
              "text": "依维柯",
              "id": 96
            }
          ]
        }
      ]
    },
    {
      "text": "O",
      "children": [
        {
          "value": "1124,1269,1048,1047,695,938,937,802,936,402",
          "text": "欧宝",
          "id": 80,
          "children": [
            {
              "value": "1124,1269,1048,1047,695,938,937,802,936,402",
              "text": "欧宝",
              "id": 70
            }
          ]
        },
        {
          "value": "399,345,344,300,299,298,3073,238,1826,205,2845",
          "text": "讴歌",
          "id": 81,
          "children": [
            {
              "value": "399,345,344,300,299,298,3073,238,1826,205,2845",
              "text": "讴歌",
              "id": 71
            }
          ]
        }
      ]
    },
    {
      "text": "P",
      "children": [
        {
          "value": "5312",
          "text": "Polestar",
          "id": 763,
          "children": [
            {
              "value": "5312",
              "text": "Polestar",
              "id": 725
            }
          ]
        }
      ]
    },
    {
      "text": "Q",
      "children": [
        {
          "value": "1362,1735,589,220,219,218,217",
          "text": "青年汽车",
          "id": 82,
          "children": [
            {
              "value": "1362,589,220,219,218,217",
              "text": "莲花",
              "id": 60
            },
            {
              "value": "1735",
              "text": "青年",
              "id": 222
            }
          ]
        },
        {
          "value": "1674,664,2463,4708,5129",
          "text": "奇瑞捷豹路虎",
          "id": 83,
          "children": [
            {
              "value": "1674,664",
              "text": "路虎",
              "id": 59
            },
            {
              "value": "2463,4708,5129",
              "text": "捷豹",
              "id": 47
            }
          ]
        },
        {
          "value": "6053,1086,4172,1171,1087,1313,1314,1270,1315,5252,4173,4170,1170,1360,4169,2165,3092,1727,4196,862,860,859,4825,2291,5993,5818,2711,4522,2712,4392,4186,4185,500,499,498,989,415,4183,2383,414,1016,413,4201,784,783,1852,4200,782,1049,4199,781,4198,780,4197,779,778,5040,4194,4568,772,4193,771,4192,770,4191,4190,4189,4188,4187,762,761,760,759,758,2001,5245,617,616,4195,861,4171,946,4184,450,449,3026,4179,457,1834,4182,4181,4180,280,279,278,277,4178,141,72,4176,4175,69,68,4174,62,6034,2626,2543,5817,5225,6133",
          "text": "奇瑞汽车",
          "id": 84,
          "children": [
            {
              "value": "4172,1171,1270,1315,5252,4173,4170,1170,1360,4169,4825,5993,5818,2711,2001,5245,617,616,4171,946",
              "text": "开瑞",
              "id": 55
            },
            {
              "value": "1087,4196,862,860,859,4195,861",
              "text": "威麟",
              "id": 88
            },
            {
              "value": "1086,1313,1314,2165,3092,1727,2291,4522,2712,4392,4186,4185,500,499,498,989,415,4183,2383,414,1016,413,4201,784,783,1852,4200,782,1049,4199,781,4198,780,4197,779,778,5040,4194,4568,772,4193,771,4192,770,4191,4190,4189,4188,4187,762,761,760,759,758,4184,450,449,3026,4179,457,1834,4182,4181,4180,280,279,278,277,4178,141,72,4176,4175,69,68,4174,62,6034,2626,2543,5817,5225,6133",
              "text": "奇瑞",
              "id": 73
            },
            {
              "value": "6053",
              "text": "捷途",
              "id": 825
            }
          ]
        },
        {
          "value": "1089,1316,1361,1088,1125,436,815,812,813,887,628,362,215,214,2810,4672",
          "text": "起亚",
          "id": 85,
          "children": [
            {
              "value": "1089,1316,1361,1088,1125,436,815,812,813,887,628,362,215,214,2810,4672",
              "text": "起亚",
              "id": 74
            }
          ]
        },
        {
          "value": "6013",
          "text": "前途汽车",
          "id": 682,
          "children": [
            {
              "value": "6013",
              "text": "前途",
              "id": 645
            }
          ]
        },
        {
          "value": "1172,1050",
          "text": "庆铃汽车",
          "id": 266,
          "children": [
            {
              "value": "1172,1050",
              "text": "庆铃",
              "id": 169
            }
          ]
        }
      ]
    },
    {
      "text": "R",
      "children": [
        {
          "value": "1127,1363,1218,1174,1052,1173,1317,1126,1219,1051,1364,1318,1271,1365,1272,845,509,188,27,26,5306",
          "text": "日产",
          "id": 86,
          "children": [
            {
              "value": "1127,1363,1218,1174,1052,1173,1317,1126,1219,1051,1364,1318,1271,1365,1272,845,509,188,27,26,5306",
              "text": "日产",
              "id": 75
            }
          ]
        }
      ]
    },
    {
      "text": "S",
      "children": [
        {
          "value": "667,662,721,720,506,730,729,584,923,2548",
          "text": "三菱",
          "id": 96,
          "children": [
            {
              "value": "667,662,721,720,506,730,729,584,923,2548",
              "text": "三菱",
              "id": 83
            }
          ]
        },
        {
          "value": "1222,1055,1368,1367,1223,1595,604,2663",
          "text": "双龙",
          "id": 97,
          "children": [
            {
              "value": "1222,1055,1368,1367,1223,1595,604,2663",
              "text": "双龙",
              "id": 82
            }
          ]
        },
        {
          "value": "818,411,410,756,430,809,466,620,4062,4061,805,804,4510,103,4060,101,4059,96,94,4051,37,4050,33,4049,23,21,19,18,17,4048,14,4047,4046,10,9,7,5,1616,4389,2704,4615,3091,2623,5895",
          "text": "神龙汽车",
          "id": 98,
          "children": [
            {
              "value": "4051,37,4050,33,4049,23,21,19,18,17,4048,14,4047,4046,10,9,7,5,4389,2704,4615,3091",
              "text": "标致",
              "id": 17
            },
            {
              "value": "818,411,410,756,430,809,466,620,4062,4061,805,804,4510,103,4060,101,4059,96,94,1616,2623,5895",
              "text": "雪铁龙",
              "id": 92
            }
          ]
        },
        {
          "value": "361,3012,2279,4215,166,4529,4447",
          "text": "上汽商用车",
          "id": 99,
          "children": [
            {
              "value": "361,3012,2279,4215,166,4529,4447",
              "text": "上汽大通",
              "id": 85
            }
          ]
        },
        {
          "value": "1091",
          "text": "上海汇众",
          "id": 259,
          "children": [
            {
              "value": "1091",
              "text": "汇众",
              "id": 130
            }
          ]
        },
        {
          "value": "1823,164,2203",
          "text": "SMART",
          "id": 4,
          "children": [
            {
              "value": "1823,164,2203",
              "text": "SMART",
              "id": 5
            }
          ]
        },
        {
          "value": "639,637,1275,1276,2717,1128,1176,1734,4221,526,864,52,4222,49,46,978,1014,4725,2893,2892,4570,4369,2503,5333",
          "text": "上汽通用五菱",
          "id": 100,
          "children": [
            {
              "value": "637,1734,52,4222,49,46,1014,4725,2893,2892,4369,2503,5333",
              "text": "宝骏",
              "id": 8
            },
            {
              "value": "1275,1276,2717,1128,1176,4221,526,864,978,4570",
              "text": "五菱",
              "id": 89
            },
            {
              "value": "639",
              "text": "雪佛兰",
              "id": 91
            }
          ]
        },
        {
          "value": "4752",
          "text": "时空电动",
          "id": 622,
          "children": [
            {
              "value": "4752",
              "text": "时空电动",
              "id": 566
            }
          ]
        },
        {
          "value": "1090",
          "text": "三星",
          "id": 273,
          "children": [
            {
              "value": "1090",
              "text": "三星",
              "id": 146
            }
          ]
        },
        {
          "value": "1220",
          "text": "陕汽通家",
          "id": 274,
          "children": [
            {
              "value": "1220",
              "text": "陕汽通家",
              "id": 147
            }
          ]
        },
        {
          "value": "1175,57",
          "text": "萨博",
          "id": 87,
          "children": [
            {
              "value": "1175,57",
              "text": "萨博",
              "id": 77
            }
          ]
        },
        {
          "value": "444,4621,909,908,810,665,657,405,6116,391,92",
          "text": "斯巴鲁",
          "id": 88,
          "children": [
            {
              "value": "444,4621,909,908,810,665,657,405,6116,391,92",
              "text": "斯巴鲁",
              "id": 78
            }
          ]
        },
        {
          "value": "501,5814,2750,843,842,5813,832,831,829,830,993,742,741,641,267,266,6114,5812,676,5431,674,671,649,162,582,4375,1475,692,912,537,824,878,898,2806,4918,2280,3010,5893,4931,5256",
          "text": "上汽大众",
          "id": 89,
          "children": [
            {
              "value": "162,582,4375,1475,692,912,537,824,878,898,4918,3010,5256",
              "text": "斯柯达",
              "id": 81
            },
            {
              "value": "501,5814,2750,843,842,5813,832,831,829,830,993,742,741,641,267,266,6114,5812,676,5431,674,671,649,2806,2280,5893,4931",
              "text": "大众",
              "id": 31
            }
          ]
        },
        {
          "value": "5305",
          "text": "四川现代",
          "id": 762,
          "children": [
            {
              "value": "5305",
              "text": "现代",
              "id": 90
            }
          ]
        },
        {
          "value": "1273,1054,1221,1053,429,515,546,528,4123,539,547",
          "text": "上海华普",
          "id": 90,
          "children": [
            {
              "value": "1273,1054,1221,1053,429,515,546,528,4123,539,547",
              "text": "华普",
              "id": 42
            }
          ]
        },
        {
          "value": "1385,2240,1454,1474,785,4214,363,4207,246,4206,4205,4905,244,245,4204,243,4203,242,241,4202,240,4208,239,4213,142,2179,4665,4212,60,1817,4211,54,4775,4210,562,41,1813,4209,1,4777,4753,2746,2900,3069,2952,4645,3105,4776,4449,2721,2341,5673,5251,5085,5413,5186,6193",
          "text": "上海汽车",
          "id": 91,
          "children": [
            {
              "value": "1474,785,4207,246,4206,4205,4905,244,245,4204,243,4203,242,241,4202,240,4208,239,3069,2952,6193",
              "text": "MG",
              "id": 3
            },
            {
              "value": "1385,2240,1454,4214,363,4213,142,2179,4665,4212,60,1817,4211,54,4775,4210,562,41,1813,4209,1,4777,4753,2746,2900,4645,3105,4776,4449,2721,2341,5673,5251,5085,5413,5186",
              "text": "荣威",
              "id": 76
            }
          ]
        },
        {
          "value": "633,882,326",
          "text": "双环汽车",
          "id": 92,
          "children": [
            {
              "value": "633,882,326",
              "text": "双环",
              "id": 79
            }
          ]
        },
        {
          "value": "390,335,4220,329,81,5418,4224,2504,1999,694,4226,4225,821,822,609,610,608,614,418,417,559,5652,443,638,4223,647,332,788,4219,928,925,4218,675,4216,407,2000,408,4217,2464,587,5250,4385,583,626,625,627,176,1366,1274,2345,2765,1554,4756,4347,1720,1729,1728,996,4757,2865,4755,2905,4754,4546,4758,4547,2926,2486,5128,6173",
          "text": "上汽通用",
          "id": 93,
          "children": [
            {
              "value": "390,335,4220,329,81,1366,2345,2765,1554,4756,4347,1720,5128",
              "text": "凯迪拉克",
              "id": 53
            },
            {
              "value": "788,4219,928,925,4218,675,4216,407,2000,408,4217,2464,587,5250,4385,583,626,625,627,176,1274,1728,996,4755,2905,4754,4546,4758,4547",
              "text": "别克",
              "id": 10
            },
            {
              "value": "5418,4224,2504,1999,694,4226,4225,821,822,609,610,608,614,418,417,559,5652,443,638,4223,647,332,1729,4757,2865,2926,2486,6173",
              "text": "雪佛兰",
              "id": 91
            }
          ]
        },
        {
          "value": "106",
          "text": "世爵",
          "id": 94,
          "children": [
            {
              "value": "106",
              "text": "世爵",
              "id": 80
            }
          ]
        },
        {
          "value": "1224,1320,1130,392,538,841,994",
          "text": "斯柯达",
          "id": 95,
          "children": [
            {
              "value": "1224,1320,1130,392,538,841,994",
              "text": "斯柯达",
              "id": 81
            }
          ]
        }
      ]
    },
    {
      "text": "T",
      "children": [
        {
          "value": "3052,3055,2758,2968,2759,2760",
          "text": "泰卡特",
          "id": 421,
          "children": [
            {
              "value": "3052,3055,2758,2968,2759,2760",
              "text": "泰卡特",
              "id": 303
            }
          ]
        },
        {
          "value": "1278,1132,1321",
          "text": "天马汽车",
          "id": 261,
          "children": [
            {
              "value": "1278,1132,1321",
              "text": "天马",
              "id": 131
            }
          ]
        },
        {
          "value": "991,581,875,4230,874,4229,4228,877,876,4231,873,4227,858,4233,4232,895,894,893,892,1369,1277,4377,4616,4384,2506,5191,5453,5005",
          "text": "天津一汽",
          "id": 101,
          "children": [
            {
              "value": "991,581,875,4230,874,4229,4228,877,876,4231,873,4227,858,4233,4232,895,894,893,892,1369,1277,4377,4616,4384,2506,5191,5453,5005",
              "text": "一汽",
              "id": 95
            }
          ]
        },
        {
          "value": "1370",
          "text": "天汽美亚",
          "id": 294,
          "children": [
            {
              "value": "1370",
              "text": "美亚",
              "id": 170
            }
          ]
        },
        {
          "value": "1131,2207,5693",
          "text": "特斯拉",
          "id": 295,
          "children": [
            {
              "value": "1131,2207,5693",
              "text": "特斯拉",
              "id": 162
            }
          ]
        }
      ]
    },
    {
      "text": "W",
      "children": [
        {
          "value": "1183,1615,2161,2645,5852",
          "text": "潍柴汽车",
          "id": 289,
          "children": [
            {
              "value": "1183,1615,2161,2645,5852",
              "text": "英致",
              "id": 182
            }
          ]
        },
        {
          "value": "5267",
          "text": "威马汽车",
          "id": 722,
          "children": [
            {
              "value": "5267",
              "text": "威马",
              "id": 685
            }
          ]
        },
        {
          "value": "1093,1092,1322",
          "text": "万丰汽车",
          "id": 293,
          "children": [
            {
              "value": "1093,1092,1322",
              "text": "万丰",
              "id": 132
            }
          ]
        },
        {
          "value": "1842,382,380,359,355,315,105,98,5932,1323,1371,1056,2204,3064,4521",
          "text": "沃尔沃",
          "id": 102,
          "children": [
            {
              "value": "1842,382,380,359,355,315,105,98,5932,1323,1371,1056,2204,3064,4521",
              "text": "沃尔沃",
              "id": 87
            }
          ]
        },
        {
          "value": "5824",
          "text": "瓦滋",
          "id": 823,
          "children": [
            {
              "value": "5824",
              "text": "瓦滋",
              "id": 785
            }
          ]
        },
        {
          "value": "4805,381,379,5249,1837,316,5612,2729,5130",
          "text": "沃尔沃亚太",
          "id": 103,
          "children": [
            {
              "value": "4805,381,379,5249,1837,316,5612,2729,5130",
              "text": "沃尔沃",
              "id": 87
            }
          ]
        },
        {
          "value": "4785",
          "text": "蔚来汽车",
          "id": 601,
          "children": [
            {
              "value": "4785",
              "text": "蔚来",
              "id": 545
            }
          ]
        },
        {
          "value": "1133",
          "text": "威兹曼",
          "id": 268,
          "children": [
            {
              "value": "1133",
              "text": "威兹曼",
              "id": 140
            }
          ]
        }
      ]
    },
    {
      "text": "X",
      "children": [
        {
          "value": "1280,2774,2947,2948",
          "text": "新凯汽车",
          "id": 276,
          "children": [
            {
              "value": "1280,2774,2947,2948",
              "text": "新凯",
              "id": 171
            }
          ]
        },
        {
          "value": "2784",
          "text": "厦门金龙",
          "id": 422,
          "children": [
            {
              "value": "2784",
              "text": "金旅",
              "id": 323
            }
          ]
        },
        {
          "value": "1279",
          "text": "新大地汽车",
          "id": 264,
          "children": [
            {
              "value": "1279",
              "text": "新大地",
              "id": 155
            }
          ]
        },
        {
          "value": "1134,1324,1372,1325,1177,1373,1094,1178,1374,485,924,949,865,820,507,564,646,645,899,196",
          "text": "现代",
          "id": 104,
          "children": [
            {
              "value": "1134,1324,1372,1325,1177,1373,1094,1178,1374,485,924,949,865,820,507,564,646,645,899,196",
              "text": "现代",
              "id": 90
            }
          ]
        },
        {
          "value": "611,615,863,825,1095,1375,1281,5452",
          "text": "雪佛兰",
          "id": 105,
          "children": [
            {
              "value": "611,615,863,825,1095,1375,1281,5452",
              "text": "雪佛兰",
              "id": 91
            }
          ]
        },
        {
          "value": "100,99,102,1282,1326,1096,1179",
          "text": "雪铁龙",
          "id": 106,
          "children": [
            {
              "value": "100,99,102,1282,1326,1096,1179",
              "text": "雪铁龙",
              "id": 92
            }
          ]
        },
        {
          "value": "726,911,910,222",
          "text": "西雅特",
          "id": 107,
          "children": [
            {
              "value": "726,911,910,222",
              "text": "西雅特",
              "id": 93
            }
          ]
        },
        {
          "value": "4750",
          "text": "小鹏汽车",
          "id": 621,
          "children": [
            {
              "value": "4750",
              "text": "小鹏",
              "id": 565
            }
          ]
        },
        {
          "value": "6153",
          "text": "新特汽车",
          "id": 863,
          "children": [
            {
              "value": "6153",
              "text": "新特",
              "id": 865
            }
          ]
        }
      ]
    },
    {
      "text": "Y",
      "children": [
        {
          "value": "1327,2969,2966",
          "text": "亚琛施纳泽",
          "id": 288,
          "children": [
            {
              "value": "1327,2969,2966",
              "text": "亚琛施纳泽",
              "id": 156
            }
          ]
        },
        {
          "value": "4625,3062,3063",
          "text": "御捷",
          "id": 481,
          "children": [
            {
              "value": "4625,3062,3063",
              "text": "御捷",
              "id": 365
            }
          ]
        },
        {
          "value": "5288",
          "text": "宇通客车",
          "id": 742,
          "children": [
            {
              "value": "5288",
              "text": "宇通",
              "id": 705
            }
          ]
        },
        {
          "value": "1285",
          "text": "跃进汽车",
          "id": 262,
          "children": [
            {
              "value": "1285",
              "text": "跃进",
              "id": 148
            }
          ]
        },
        {
          "value": "4917,4585",
          "text": "云度新能源",
          "id": 521,
          "children": [
            {
              "value": "4917,4585",
              "text": "云度",
              "id": 429
            }
          ]
        },
        {
          "value": "1182,286,285,1835,284,283,281,1833,276,274,1832,272,262,195,165,150,148,2719",
          "text": "英菲尼迪",
          "id": 108,
          "children": [
            {
              "value": "1182,286,285,1835,284,283,281,1833,276,274,1832,272,262,195,165,150,148,2719",
              "text": "英菲尼迪",
              "id": 94
            }
          ]
        },
        {
          "value": "2168,503,828,698,4234,560,884,599,433,431,108,2684,5792,271,269,4514,74,70,65,64,5145,5331",
          "text": "一汽-大众",
          "id": 109,
          "children": [
            {
              "value": "5792,271,269,4514,74,70,65,64,5145",
              "text": "奥迪",
              "id": 6
            },
            {
              "value": "2168,503,828,698,4234,560,884,599,433,431,108,2684,5331",
              "text": "大众",
              "id": 31
            }
          ]
        },
        {
          "value": "1377,1184",
          "text": "永源飞碟",
          "id": 302,
          "children": [
            {
              "value": "1377,1184",
              "text": "永源飞碟",
              "id": 172
            }
          ]
        },
        {
          "value": "789,527,525,618,739,425,735,3016,856,1846,606,644,981,295,5692",
          "text": "一汽丰田",
          "id": 110,
          "children": [
            {
              "value": "789,527,525,618,739,425,735,3016,856,1846,606,644,295,5692",
              "text": "丰田",
              "id": 32
            },
            {
              "value": "981",
              "text": "朗世",
              "id": 102
            }
          ]
        },
        {
          "value": "849,1228",
          "text": "一汽华利",
          "id": 111,
          "children": [
            {
              "value": "849,1228",
              "text": "一汽",
              "id": 95
            }
          ]
        },
        {
          "value": "4244,4243,723,722,377,89,88,87,1376,4668,1695,979,980,4928,4745,2825,4306,535,697,749,806,204,203",
          "text": "一汽轿车",
          "id": 112,
          "children": [
            {
              "value": "979,980,4928,4306,535,697,749,806,204,203",
              "text": "红旗",
              "id": 43
            },
            {
              "value": "4244,4243,723,722,377,89,88,87,1376,4668,1695,4745,2825",
              "text": "一汽",
              "id": 95
            }
          ]
        },
        {
          "value": "4241,1229,4238,1284,4236,1181,4235,1283,1395,4237,839,4242,838,4779,2206,3008,4240,3007,4239,5205",
          "text": "一汽吉林",
          "id": 113,
          "children": [
            {
              "value": "4241,1229,4238,1284,4236,1181,4235,1283,1395,4237,839,4242,838,4779,2206,3008,4240,3007,4239,5205",
              "text": "一汽",
              "id": 95
            }
          ]
        },
        {
          "value": "717,716,714,713,715,123,2343,2201",
          "text": "一汽马自达",
          "id": 114,
          "children": [
            {
              "value": "717,716,714,713,715,123,2343,2201",
              "text": "马自达",
              "id": 68
            }
          ]
        },
        {
          "value": "964",
          "text": "一汽通用红塔",
          "id": 115,
          "children": [
            {
              "value": "964",
              "text": "一汽",
              "id": 95
            }
          ]
        },
        {
          "value": "5672",
          "text": "云雀汽车",
          "id": 275,
          "children": [
            {
              "value": "5672",
              "text": "云雀",
              "id": 136
            }
          ]
        },
        {
          "value": "1057,1227,1097,1721,1722,2899,983,4519,4468,3011",
          "text": "野马汽车",
          "id": 120,
          "children": [
            {
              "value": "1057,1227,1097,1721,1722,2899,983,4519,4468,3011",
              "text": "野马",
              "id": 104
            }
          ]
        },
        {
          "value": "1180,1226",
          "text": "扬子汽车",
          "id": 285,
          "children": [
            {
              "value": "1180,1226",
              "text": "扬子",
              "id": 157
            }
          ]
        }
      ]
    },
    {
      "text": "Z",
      "children": [
        {
          "value": "1387,1384",
          "text": "中顺汽车",
          "id": 305,
          "children": [
            {
              "value": "1387,1384",
              "text": "中顺",
              "id": 175
            }
          ]
        },
        {
          "value": "1139,1059,4296,1140,2241,1556,2423,1736,952,683,2727,905,655,2443,5030,4301,3028,398,4300,3089,396,4299,4298,395,394,4297,393,4295,347,4294,4327,341,4293,340,1828,4292,229,1812,4291,36,4290,6,5029,1759,4759,2897,4485,1899,5027,2710,4781,4948,4914,4505,5043,1737,5028,2299,5032,2829,5166",
          "text": "众泰汽车",
          "id": 116,
          "children": [
            {
              "value": "952",
              "text": "知豆",
              "id": 97
            },
            {
              "value": "1139,1059,4296,1140,2241,1556,2423,1736,683,2727,905,655,2443,5030,4301,3028,398,4300,3089,396,4299,4298,395,394,4297,393,4295,347,4294,4327,341,4293,340,1828,4292,229,1812,4291,36,4290,6,5029,1759,4759,2897,4485,1899,5027,2710,4781,4948,4914,4505,5043,1737,5028,2299,5032,2829,5166",
              "text": "众泰",
              "id": 99
            }
          ]
        },
        {
          "value": "4286,445,491,4288,870,4287,747,4289,1187,1138,973,976,2775",
          "text": "中兴汽车",
          "id": 117,
          "children": [
            {
              "value": "4286,445,491,4288,870,4287,747,4289,1187,1138,973,976,2775",
              "text": "中兴",
              "id": 100
            }
          ]
        },
        {
          "value": "4285,939,4282,736,4608,4284,807,4283,400,4281,263,258,1135,1378,1185,1186,4056,1107,1136,1137,4365,4763,2718,5189",
          "text": "郑州日产",
          "id": 118,
          "children": [
            {
              "value": "4285,939,4608,4284,807,4283,400,1135,1185,1186,4056,1107,1136,1137",
              "text": "东风",
              "id": 23
            },
            {
              "value": "258,4365,4763,2718",
              "text": "东风风度",
              "id": 24
            },
            {
              "value": "4282,736,4281,263,1378,5189",
              "text": "日产",
              "id": 75
            }
          ]
        },
        {
          "value": "995,1879,4646",
          "text": "知豆电动车",
          "id": 139,
          "children": [
            {
              "value": "995,1879,4646",
              "text": "知豆",
              "id": 97
            }
          ]
        },
        {
          "value": "1379",
          "text": "中誉汽车",
          "id": 283,
          "children": [
            {
              "value": "1379",
              "text": "中誉",
              "id": 173
            }
          ]
        },
        {
          "value": "2950,2951",
          "text": "浙江卡尔森",
          "id": 460,
          "children": [
            {
              "value": "2950,2951",
              "text": "浙江卡尔森",
              "id": 344
            }
          ]
        }
      ]
    }
  ]
}