{
  "result_code": "200",
  "result_msg": "执行成功",
  "data": [
    {
      "incents": {
        "columns": [
          {
            "title": "年度销售激励:396840",
            "children": [
              {
                "key": "discount",
                "title": "固定折扣"
              },
              {
                "key": "kpi",
                "title": "考核奖励"
              }
            ]
          },
          {
            "title": "11月销售激励:274000",
            "children": [
              {
                "key": "item1",
                "title": "AaK销售目标达成奖"
              },
              {
                "key": "item2",
                "title": "A级车销售达成奖"
              },
              {
                "key": "item3",
                "title": "专注贡献奖"
              },
              {
                "key": "item4",
                "title": "保险支持"
              },
              {
                "key": "item5",
                "title": "库存补偿"
              },
              {
                "key": "item6",
                "title": "销售提升奖"
              }
            ]
          },
          {
            "title": "12月销售激励:274000",
            "children": [
              {
                "key": "item7",
                "title": "AaK销售目标达成奖"
              },
              {
                "key": "item8",
                "title": "A级车销售达成奖"
              },
              {
                "key": "item9",
                "title": "专注贡献奖"
              },
              {
                "key": "item10",
                "title": "保险支持"
              },
              {
                "key": "item11",
                "title": "库存补偿"
              },
              {
                "key": "item12",
                "title": "销售提升奖"
              }
            ]
          },
          {
            "key": "mtotal",
            "title": "12月小计"
          }
        ],
        "dataSource": [
          {
            "key": 1,
            "mtotal": 72920,
            "item2": 22000,
            "item1": 165000,
            "kpi": 145840,
            "discount": 251000,
            "item12": 33000,
            "item11": 5600,
            "item10": 48400,
            "item8": 22000,
            "item7": 165000,
            "item9": 0,
            "item4": 48400,
            "item3": 0,
            "item6": 33000,
            "item5": 5600
          }
        ]
      },
      "profits": {
        "title": [
          "1月",
          "2月",
          "3月",
          "4月",
          "5月",
          "6月",
          "7月",
          "8月",
          "9月",
          "10月",
          "11月",
          "12月"
        ],
        "data": [
          -3435,
          -1116,
          -784,
          -415,
          -616,
          -35,
          -361,
          -1946,
          -2402,
          -3243,
          -3219,
          -1456
        ]
      },
      "details": {
        "title": [
          "1月",
          "2月",
          "3月",
          "4月",
          "5月",
          "6月",
          "7月",
          "8月",
          "9月",
          "10月",
          "11月",
          "12月"
        ],
        "sales": [
          88,
          51,
          141,
          105,
          157,
          129,
          134,
          165,
          254,
          172,
          279,
          232
        ],
        "msrp": [
          12.26,
          12.25,
          12.26,
          12.26,
          12.32,
          12.35,
          12.37,
          12.36,
          12.33,
          12.3,
          12.31,
          12.28
        ],
        "tp": [
          10.52,
          10.74,
          10.86,
          10.56,
          10.31,
          10.27,
          10.19,
          10.03,
          9.95,
          9.82,
          9.88,
          10.04
        ],
        "lp": [
          0,
          0,
          0,
          0,
          0,
          0,
          0,
          0,
          0,
          0,
          0,
          0
        ],
        "titleText": "宝来单车价格策略价格表现",
        "cycle": [
          null,
          null,
          "年式变化",
          null,
          null,
          null,
          null,
          null,
          "年式变化",
          null,
          null,
          null
        ]
      }
    }
  ]
}